Metadata-Version: 2.1
Name: GlobalVars
Version: 0.0.5
Summary: Using environment variable to store global vars to the enrite project
Home-page: https://github.com/mrotame/GlobalVars
Author: Matheus Menezes Almeida
Author-email: mrotame@gmail.com
License: UNKNOWN
Platform: UNKNOWN
Classifier: Programming Language :: Python :: 3
Classifier: License :: OSI Approved :: MIT License
Classifier: Operating System :: OS Independent
Requires-Python: >=3.6
